waypaper/__main__.py
waypaper/app.py
waypaper/changer.py
waypaper/common.py
waypaper/config.py
waypaper/options.py
waypaper/translations.py
waypaper/waypaperd.py
waypaper-2.7.data/data/share/applications/waypaper.desktop
waypaper-2.7.data/data/share/icons/hicolor/scalable/apps/waypaper.svg
waypaper-2.7.data/data/share/man/man1/waypaper.1.gz
waypaper-2.7.dist-info/licenses/LICENSE
waypaper-2.7.dist-info/METADATA
waypaper-2.7.dist-info/WHEEL
waypaper-2.7.dist-info/entry_points.txt
waypaper-2.7.dist-info/top_level.txt
waypaper-2.7.dist-info/RECORD
