Metadata-Version: 2.4
Name: waypaper
Version: 2.7
Summary: GUI wallpaper setter for Wayland
Home-page: https://github.com/anufrievroman/waypaper
Author: Roman Anufriev
Author-email: anufriev.roman@protonmail.com
License: GPL
Classifier: Development Status :: 4 - Beta
Classifier: License :: OSI Approved :: GNU General Public License (GPL)
Classifier: Environment :: Console
Classifier: Natural Language :: English
Classifier: Operating System :: OS Independent
Classifier: Programming Language :: Python :: 3.10
Classifier: Programming Language :: Python :: 3.11
Classifier: Programming Language :: Python :: 3.12
Classifier: Topic :: Utilities
Requires-Python: >3.10
License-File: LICENSE
Requires-Dist: PyGObject
Requires-Dist: platformdirs
Requires-Dist: Pillow
Requires-Dist: imageio
Requires-Dist: imageio-ffmpeg
Requires-Dist: screeninfo
Dynamic: author
Dynamic: author-email
Dynamic: classifier
Dynamic: description
Dynamic: description-content-type
Dynamic: home-page
Dynamic: license
Dynamic: license-file
Dynamic: requires-dist
Dynamic: requires-python
Dynamic: summary
